HISTORY.txt
LICENSE
MANIFEST.in
README.md
pyproject.toml
rcsb/__init__.py
rcsb.utils.insilico3d.egg-info/PKG-INFO
rcsb.utils.insilico3d.egg-info/SOURCES.txt
rcsb.utils.insilico3d.egg-info/dependency_links.txt
rcsb.utils.insilico3d.egg-info/requires.txt
rcsb.utils.insilico3d.egg-info/top_level.txt
rcsb/utils/__init__.py
rcsb/utils/insilico3d/AlphaFoldModelCloudProvider.py
rcsb/utils/insilico3d/AlphaFoldModelProvider.py
rcsb/utils/insilico3d/ModelArchiveModelProvider.py
rcsb/utils/insilico3d/ModelHoldingsProvider.py
rcsb/utils/insilico3d/ModelProviderWorkflow.py
rcsb/utils/insilico3d/ModelReorganizer.py
rcsb/utils/insilico3d/__init__.py