Metadata-Version: 2.4
Name: rcsb.utils.insilico3d
Version: 0.42
Summary: RCSB Python In Silico Model Access Utilities
Author-email: Dennis Piehl <dennis.piehl@rcsb.org>
License-Expression: Apache-2.0
Project-URL: Homepage, https://github.com/rcsb/py-rcsb_utils_insilico3d
Classifier: Development Status :: 5 - Production/Stable
Classifier: Intended Audience :: Developers
Classifier: Natural Language :: English
Classifier: Programming Language :: Python
Classifier: Programming Language :: Python :: 3
Classifier: Programming Language :: Python :: 3.13
Requires-Python: >=3.9
License-File: LICENSE
Requires-Dist: rcsb.utils.io>=1.52
Requires-Dist: rcsb.utils.multiproc>=0.21
Requires-Dist: asyncio>=3.4.3
Requires-Dist: aiohttp>=3.12.7
Requires-Dist: aiofiles>=24.1.0
Provides-Extra: cloud
Requires-Dist: gsutil>=5.14; extra == "cloud"
Requires-Dist: google-cloud-storage>=2.5.0; extra == "cloud"
Provides-Extra: dev
Requires-Dist: check-manifest; extra == "dev"
Provides-Extra: tests
Requires-Dist: tox; extra == "tests"
Requires-Dist: pylint; extra == "tests"
Requires-Dist: black>=21.5b1; extra == "tests"
Requires-Dist: flake8; extra == "tests"
Requires-Dist: coverage; extra == "tests"
Dynamic: license-file
